{
	"serverVersion" : "static",
	"wins": 0,
	"prefix": "https://i.imgur.com/",
	"winnerThreshold": 1000,
	"expected": {
		"left": "fDL2Ubb.png",
		"right": "fDL2Ubb.png"
	},
	"totalWinners": 0,
	"accountIsInvalidFlag": true,
	"time": 5000,
	"slowDownFlag": false,
	"losses": 0,
	"maxWinners": 10,
	"choices": [
		{
			"left": "5pO5dq7.png",
			"right": "vpyezNk.png"
		},
		{
			"left": "vpyezNk.png",
			"right": "q4kN3u4.png"
		},
		{
			"left": "q4kN3u4.png",
			"right": "q4kN3u4.png"
		},
		{
			"left": "fDL2Ubb.png",
			"right": "ERMOMYF.png"
		},
		{
			"left": "5pO5dq7.png",
			"right": "q4kN3u4.png"
		},
		{
			"left": "JTP0UKz.png",
			"right": "fDL2Ubb.png"
		},
		{
			"left": "q4kN3u4.png",
			"right": "fDL2Ubb.png"
		},
		{
			"left": "fDL2Ubb.png",
			"right": "fDL2Ubb.png"
		},
		{
			"left": "5pO5dq7.png",
			"right": "fDL2Ubb.png"
		},
		{
			"left": "JTP0UKz.png",
			"right": "5pO5dq7.png"
		},
		{
			"left": "ERMOMYF.png",
			"right": "5pO5dq7.png"
		},
		{
			"left": "fDL2Ubb.png",
			"right": "5pO5dq7.png"
		},
		{
			"left": "5pO5dq7.png",
			"right": "5pO5dq7.png"
		},
		{
			"left": "JTP0UKz.png",
			"right": "vpyezNk.png"
		},
		{
			"left": "ERMOMYF.png",
			"right": "vpyezNk.png"
		},
		{
			"left": "fDL2Ubb.png",
			"right": "JTP0UKz.png"
		}
	]
}